meta_learn/__init__.py
meta_learn/base_meta_regressor.py
meta_learn/meta_learn_core.py
meta_learn/paths.py
meta_learn/pretrained_meta_regressors/tabular/regression/decision_tree_classifier.joblib
meta_learn/tabular/__init__.py
meta_learn/tabular/classification/__init__.py
meta_learn/tabular/classification/meta_regressor.py
meta_learn/tabular/regression/__init__.py
meta_learn/tabular/regression/default_reference_datasets.py
meta_learn/tabular/regression/default_reference_models.py
meta_learn/tabular/regression/meta_learn.py
meta_learn/tabular/regression/meta_regressor.py
meta_learn-0.2.0.dist-info/LICENSE
meta_learn-0.2.0.dist-info/METADATA
meta_learn-0.2.0.dist-info/WHEEL
meta_learn-0.2.0.dist-info/top_level.txt
meta_learn-0.2.0.dist-info/RECORD
